diffiehellman/__init__.py
diffiehellman/diffie_hellman.py
diffiehellman/primes.py
py_diffie_hellman-1.0.1.dist-info/LICENSE
py_diffie_hellman-1.0.1.dist-info/METADATA
py_diffie_hellman-1.0.1.dist-info/WHEEL
py_diffie_hellman-1.0.1.dist-info/top_level.txt
py_diffie_hellman-1.0.1.dist-info/RECORD
